setup.py
bin/py_send_nsca
send_nsca/__init__.py
send_nsca/nagios.py
send_nsca/nsca.py
send_nsca.egg-info/PKG-INFO
send_nsca.egg-info/SOURCES.txt
send_nsca.egg-info/dependency_links.txt
send_nsca.egg-info/requires.txt
send_nsca.egg-info/top_level.txt