Metadata-Version: 1.1
Name: send-nsca
Version: 0.1.4.1
Summary: pure-python nsca sender
Home-page: http://github.com/Roguelazer/send_nsca
Author: Yelp
Author-email: yelplabs@yelp.com
License: UNKNOWN
Platform: UNKNOWN
Classifier: Programming Language :: Python
Classifier: Operating System :: OS Independent
Classifier: License :: OSI Approved :: GNU Lesser General Public License v2 (LGPLv2)
Classifier: Topic :: System :: Monitoring
Classifier: Intended Audience :: Developers
Classifier: Development Status :: 4 - Beta
Provides: send_nsca
